{
 "align_labels_right": 0, 
 "creation": "2019-04-21 14:50:17.806235", 
 "css": ".print-format {\n    font-size: 8.4pt;\n    font-family: \"Helvetica Bold\";\n}\n\n.body {\n    font-size: 8.4pt;\n    line-height: 1;\n    \n}\n\ntable, th{\n    border: 1px solid black;\n    border-collapse: collapse;\n    height:35%;\n}\n\ntd {\n  border: 1px solid black;\n  border-collapse: collapse;\n}\n\nthead {display: table-header-group;}\n", 
 "custom_format": 1, 
 "disabled": 0, 
 "doc_type": "Memos", 
 "docstatus": 0, 
 "doctype": "Print Format", 
 "font": "Default", 
 "html": "{% include \"templates/print_formats/memo/memo.html\" %}", 
 "idx": 0, 
 "line_breaks": 0, 
 "modified": "2019-04-21 14:50:17.806235", 
 "modified_by": "Administrator", 
 "module": "Tablix HR", 
 "name": "Memo", 
 "owner": "Administrator", 
 "print_format_builder": 0, 
 "print_format_type": "Server", 
 "show_section_headings": 0, 
 "standard": "Yes"
}